napari_fluoresfm/__init__.py
napari_fluoresfm/_reader.py
napari_fluoresfm/_sample_data.py
napari_fluoresfm/_version.py
napari_fluoresfm/_widget.py
napari_fluoresfm/_writer.py
napari_fluoresfm/base_widgts.py
napari_fluoresfm/napari.yaml
napari_fluoresfm/_tests/__init__.py
napari_fluoresfm/_tests/test_reader.py
napari_fluoresfm/_tests/test_sample_data.py
napari_fluoresfm/_tests/test_widget.py
napari_fluoresfm/_tests/test_writer.py
napari_fluoresfm/fluoresfm/models/biomedclip_embedder.py
napari_fluoresfm/fluoresfm/models/unet_attention.py
napari_fluoresfm/fluoresfm/models/unet_sd_c.py
napari_fluoresfm/fluoresfm/preprocess/embdedding.py
napari_fluoresfm/fluoresfm/preprocess/patching.py
napari_fluoresfm/fluoresfm/test/predict.py
napari_fluoresfm/fluoresfm/train/train.py
napari_fluoresfm/fluoresfm/utils/data.py
napari_fluoresfm/fluoresfm/utils/evaluation.py
napari_fluoresfm/fluoresfm/utils/loss_functions.py
napari_fluoresfm/fluoresfm/utils/optim.py
napari_fluoresfm/images/interface.png
napari_fluoresfm-0.2.3.dist-info/licenses/LICENSE
napari_fluoresfm-0.2.3.dist-info/METADATA
napari_fluoresfm-0.2.3.dist-info/WHEEL
napari_fluoresfm-0.2.3.dist-info/entry_points.txt
napari_fluoresfm-0.2.3.dist-info/top_level.txt
napari_fluoresfm-0.2.3.dist-info/RECORD
