Metadata-Version: 2.4
Name: napari-fluoresfm
Version: 0.2.3
Summary: A plugin to use FluoResFM model in napari.
Author: Qiqi Lu
Author-email: 136303971@qq.com
License: 
Project-URL: Bug Tracker, https://github.com/qiqi-lu/napari-fluoresfm/issues
Project-URL: Documentation, https://github.com/qiqi-lu/napari-fluoresfm#README.md
Project-URL: Source Code, https://github.com/qiqi-lu/napari-fluoresfm
Project-URL: User Support, https://github.com/qiqi-lu/napari-fluoresfm/issues
Classifier: Development Status :: 2 - Pre-Alpha
Classifier: Framework :: napari
Classifier: Intended Audience :: Developers
Classifier: License :: OSI Approved :: MIT License
Classifier: Operating System :: OS Independent
Classifier: Programming Language :: Python
Classifier: Programming Language :: Python :: 3
Classifier: Programming Language :: Python :: 3 :: Only
Classifier: Programming Language :: Python :: 3.10
Classifier: Programming Language :: Python :: 3.11
Classifier: Programming Language :: Python :: 3.12
Classifier: Programming Language :: Python :: 3.13
Classifier: Topic :: Scientific/Engineering :: Image Processing
Requires-Python: >=3.10
License-File: LICENSE
Requires-Dist: numpy
Requires-Dist: magicgui
Requires-Dist: qtpy
Requires-Dist: napari
Requires-Dist: scikit-image
Requires-Dist: torch
Requires-Dist: torchvision
Requires-Dist: torchaudio
Requires-Dist: tqdm
Requires-Dist: scipy
Requires-Dist: open_clip_torch
Requires-Dist: pandas
Requires-Dist: pytorch_msssim
Requires-Dist: pydicom
Requires-Dist: torchinfo
Requires-Dist: tensorboard
Requires-Dist: transformers
Requires-Dist: openpyxl
Provides-Extra: all
Requires-Dist: napari[all]; extra == "all"
Provides-Extra: testing
Requires-Dist: tox; extra == "testing"
Requires-Dist: pytest; extra == "testing"
Requires-Dist: pytest-cov; extra == "testing"
Requires-Dist: pytest-qt; extra == "testing"
Requires-Dist: napari[qt]; extra == "testing"
Dynamic: license-file
